Metadata-Version: 2.1
Name: herold
Version: 0.1.0
Requires-Python: >=3.8
Requires-Dist: pyyaml
Requires-Dist: jinja2
Requires-Dist: simple-logging-setup
Provides-Extra: dev
Requires-Dist: build ; extra == 'dev'
Requires-Dist: twine ; extra == 'dev'
Requires-Dist: tox ; extra == 'dev'
Requires-Dist: rlpython ; extra == 'dev'
Provides-Extra: test
Requires-Dist: coverage ==7.4.4 ; extra == 'test'
Requires-Dist: pytest ==8.1.1 ; extra == 'test'
